{
  "hex": "#008040",
  "general": {
    "hues": [
      "green"
    ],
    "tonality": "dark",
    "isDark": true,
    "isMidtone": false,
    "isLight": false,
    "luma": 82.432,
    "relativeLuminance": 0.158
  },
  "pairedWithLightColor": {
    "clearContrast": true,
    "contrastRatio": 4.6,
    "wcagContrast": {
      "A_normal": true,
      "AA_normal": true,
      "AA_large": true,
      "AA_ui": true,
      "AAA_normal": false,
      "AAA_large": true
    },
    "useForHeadings": true,
    "useForBodyContent": false
  },
  "pairedWithDarkColor": {
    "clearContrast": false,
    "contrastRatio": 3.1,
    "wcagContrast": {
      "A_normal": true,
      "AA_normal": false,
      "AA_large": true,
      "AA_ui": true,
      "AAA_normal": false,
      "AAA_large": false
    },
    "useForHeadings": false,
    "useForBodyContent": false
  }
}