{
  "hex": "#dd4b39",
  "general": {
    "hues": [
      "red"
    ],
    "tonality": "dark",
    "isDark": true,
    "isMidtone": false,
    "isLight": false,
    "luma": 116.602,
    "relativeLuminance": 0.206
  },
  "pairedWithLightColor": {
    "clearContrast": true,
    "contrastRatio": 3.7,
    "wcagContrast": {
      "A_normal": true,
      "AA_normal": false,
      "AA_large": true,
      "AA_ui": true,
      "AAA_normal": false,
      "AAA_large": false
    },
    "useForHeadings": false,
    "useForBodyContent": false
  },
  "pairedWithDarkColor": {
    "clearContrast": false,
    "contrastRatio": 3.8,
    "wcagContrast": {
      "A_normal": true,
      "AA_normal": false,
      "AA_large": true,
      "AA_ui": true,
      "AAA_normal": false,
      "AAA_large": false
    },
    "useForHeadings": false,
    "useForBodyContent": false
  }
}